opyni/__init__.py
opyni/exception.py
opyni/generator.py
opyni-0.1.0.dist-info/LICENSE.rst
opyni-0.1.0.dist-info/METADATA
opyni-0.1.0.dist-info/WHEEL
opyni-0.1.0.dist-info/RECORD
